LICENSE
MANIFEST.in
README
django_handlers.py
setup.py
django_handlers.egg-info/PKG-INFO
django_handlers.egg-info/SOURCES.txt
django_handlers.egg-info/dependency_links.txt
django_handlers.egg-info/not-zip-safe
django_handlers.egg-info/top_level.txt
docs/.DS_Store
docs/Makefile
docs/api.rst
docs/conf.py
docs/index.rst
docs/make.bat
docs/tutorial.rst
tests/__init__.py
tests/conftest.py
tests/test_handler.py
tests/urls.py